AUTHORS.rst
LICENSE.txt
MANIFEST.in
README.rst
setup.py
admin_reports/__init__.py
admin_reports/apps.py
admin_reports/decorators.py
admin_reports/forms.py
admin_reports/reports.py
admin_reports/sites.py
admin_reports/views.py
admin_reports/static/admin_report/css/reportlist.css
admin_reports/templates/admin/export.html
admin_reports/templates/admin/report.html
admin_reports/templates/admin/report_totals.html
django_admin_reports.egg-info/PKG-INFO
django_admin_reports.egg-info/SOURCES.txt
django_admin_reports.egg-info/dependency_links.txt
django_admin_reports.egg-info/not-zip-safe
django_admin_reports.egg-info/requires.txt
django_admin_reports.egg-info/top_level.txt